iam_sdk/__init__.py
iam_sdk/api.py
iam_sdk/config.py
iam_sdk/context.py
iam_sdk/domain/__init__.py
iam_sdk/domain/client_repository.py
iam_sdk/exceptions.py
iam_sdk/services/__init__.py
iam_sdk/services/iam.py
iam_sdk_python-0.3.0.dist-info/LICENSE
iam_sdk_python-0.3.0.dist-info/METADATA
iam_sdk_python-0.3.0.dist-info/WHEEL
iam_sdk_python-0.3.0.dist-info/RECORD
